yulang/__init__.py
yulang/_yulangpy.pyd
yulang/libatomic-1.dll
yulang/libgcc_s_seh-1.dll
yulang/libgomp-1.dll
yulang/libquadmath-0.dll
yulang/libssp-0.dll
yulang/libstdc++-6.dll
yulang/libwinpthread-1.dll
yulang/yulang.py
yulang-0.0.2.dist-info/LICENSE.md
yulang-0.0.2.dist-info/METADATA
yulang-0.0.2.dist-info/WHEEL
yulang-0.0.2.dist-info/top_level.txt
yulang-0.0.2.dist-info/RECORD
