Metadata-Version: 2.1
Name: yulang
Version: 0.0.2
Summary: yulang programming language embedded in Python
Home-page: https://github.com/yudhastyawan/yulang
Author: Yudha Styawan
Author-email: yudhastyawan@gmail.com
License: UNKNOWN
Project-URL: Bug Tracker, https://github.com/yudhastyawan/yulang/issues
Project-URL: Documentation, http://yulang.readthedocs.io
Platform: UNKNOWN
Classifier: Programming Language :: Python :: 3
Classifier: License :: OSI Approved :: GNU General Public License (GPL)
Requires-Python: >=3.8
License-File: LICENSE.md
